dimbridge/__init__.py
dimbridge/datautils.py
dimbridge/main.py
dimbridge/predicate_engine.py
dimbridge/static/widget.js
dimbridge-0.2.1.dist-info/METADATA
dimbridge-0.2.1.dist-info/WHEEL
dimbridge-0.2.1.dist-info/RECORD
