Metadata-Version: 2.3
Name: dimbridge
Version: 0.2.1
Summary: DimBridge: Interactive Explanation of Visual Patterns in Dimensionality Reductions with Predicate Logic
Requires-Dist: anywidget
Requires-Dist: ipywidgets
Requires-Dist: jupyterlab
Requires-Dist: matplotlib
Requires-Dist: natsort
Requires-Dist: numpy
Requires-Dist: pandas
Requires-Dist: torch
Requires-Dist: umap-learn
Provides-Extra: dev
Requires-Dist: jupyterlab; extra == 'dev'
Requires-Dist: watchfiles; extra == 'dev'
